LICENSE
graphlet/__init__.py
graphlet/etl/base.py
graphlet-0.1.1.dist-info/LICENSE
graphlet-0.1.1.dist-info/WHEEL
graphlet-0.1.1.dist-info/METADATA
graphlet-0.1.1.dist-info/RECORD
