Metadata-Version: 2.1
Name: graphlet
Version: 0.1.1
Summary: Graphlet AI Knowledge Graph Factory
Home-page: https://graphlet.ai
License: Apache-2.0
Keywords: graphlet,motif,graph,network,knowledge graph,entity resolution,spark,pyspark,etl
Author: Russell Jurney
Author-email: rjurney@graphlet.ai
Requires-Python: >=3.10,<4.0
Classifier: Development Status :: 1 - Planning
Classifier: Environment :: Console
Classifier: Framework :: Flake8
Classifier: Framework :: Pytest
Classifier: Framework :: tox
Classifier: Intended Audience :: Developers
Classifier: Intended Audience :: Financial and Insurance Industry
Classifier: Intended Audience :: Information Technology
Classifier: Intended Audience :: Science/Research
Classifier: License :: OSI Approved :: Apache Software License
Classifier: Natural Language :: English
Classifier: Operating System :: OS Independent
Classifier: Programming Language :: Python :: 3
Classifier: Programming Language :: Python :: 3 :: Only
Classifier: Programming Language :: Python :: 3.10
Classifier: Topic :: Database
Classifier: Topic :: Database :: Database Engines/Servers
Classifier: Topic :: Scientific/Engineering :: Artificial Intelligence
Classifier: Topic :: Scientific/Engineering :: Information Analysis
Classifier: Topic :: Software Development
Classifier: Topic :: Software Development :: Libraries :: Python Modules
Classifier: Topic :: Utilities
Classifier: Typing :: Typed
Requires-Dist: pydantic (>=1.9.1,<2.0.0)
Requires-Dist: pydantic-spark (>=0.1.1,<0.2.0)
Requires-Dist: pyspark (>=3.2.1,<4.0.0)
Requires-Dist: typeguard (>=2.13.3,<3.0.0)
Project-URL: Repository, https://github.com/Graphlet-AI/graphlet
